fast_mail_parser-0.2.5.dist-info/METADATA
fast_mail_parser-0.2.5.dist-info/WHEEL
fast_mail_parser/__init__.py
fast_mail_parser/fast_mail_parser.cpython-310-x86_64-linux-gnu.so
fast_mail_parser-0.2.5.dist-info/RECORD
