Metadata-Version: 2.1
Name: fast_mail_parser
Version: 0.2.5
Classifier: License :: OSI Approved :: Apache Software License
Classifier: Development Status :: 3 - Alpha
Classifier: Intended Audience :: Developers
Classifier: Programming Language :: Python
Classifier: Programming Language :: Rust
Classifier: Operating System :: POSIX
Classifier: Operating System :: Unix
Classifier: Topic :: Communications :: Email
Classifier: Topic :: Software Development :: Libraries
Summary: Very fast Python library for .eml files parsing.
Keywords: parser,email,rfc822,mime,maildir
Home-Page: https://github.com/namecheap/fast_mail_parser
Author: Andrii Sokyrko <wartwvister@gmail.com>
Author-email: Andrii Sokyrko <wartwvister@gmail.com>
Maintainer: Andrii Sokyrko
Maintainer-email: wartwvister@gmail.com
License: Apache-2.0
Requires-Python: >=3.7.0
Project-URL: Source Code, https://github.com/namecheap/fast_mail_parser
